cross_database_field/__init__.py
cross_database_field/admin.py
cross_database_field/apps.py
cross_database_field/fields.py
cross_database_field/forms.py
cross_database_field/models.py
cross_database_field/tests.py
cross_database_field/views.py
cross_database_field/migrations/__init__.py
django_remote_field-1.0.dist-info/METADATA
django_remote_field-1.0.dist-info/WHEEL
django_remote_field-1.0.dist-info/licenses/LICENSE
django_remote_field-1.0.dist-info/RECORD
