Metadata-Version: 2.1
Name: django-remote-field
Version: 1.0
Summary: A custom Django Field with remote database model fetching capabilities
Project-URL: Homepage, https://gitlab.com/astarivi/django-cross-database-field
Project-URL: Bug Tracker, https://gitlab.com/astarivi/django-cross-database-field/-/issues
Author: astarivi
License: MIT License
License-File: LICENSE
Classifier: Environment :: Web Environment
Classifier: Framework :: Django
Classifier: Framework :: Django :: 3.0
Classifier: Framework :: Django :: 4.0
Classifier: Intended Audience :: Developers
Classifier: License :: OSI Approved :: MIT License
Classifier: Operating System :: OS Independent
Classifier: Programming Language :: Python
Classifier: Programming Language :: Python :: 3
Classifier: Programming Language :: Python :: 3 :: Only
Classifier: Topic :: Internet :: WWW/HTTP
Classifier: Topic :: Internet :: WWW/HTTP :: Dynamic Content
Requires-Python: >=3.6
